drebedengi_sdk/__init__.py
drebedengi_sdk/client.py
drebedengi_sdk/client_async.py
drebedengi_sdk/exceptions.py
drebedengi_sdk/logger.py
drebedengi_sdk-0.1.0.dist-info/METADATA
drebedengi_sdk-0.1.0.dist-info/WHEEL
drebedengi_sdk-0.1.0.dist-info/RECORD
