Metadata-Version: 2.3
Name: drebedengi-sdk
Version: 0.1.0
Summary: 
Author: Vlad Lapikov
Author-email: 99816762+wh0t-is-love@users.noreply.github.com
Requires-Python: >=3.11
Classifier: Programming Language :: Python :: 3
Classifier: Programming Language :: Python :: 3.11
Classifier: Programming Language :: Python :: 3.12
Classifier: Programming Language :: Python :: 3.13
Requires-Dist: requests (>=2.32.3,<3.0.0)
Requires-Dist: zeep (>=4.3.1,<5.0.0)
